Metadata-Version: 2.1
Name: odoo12-addon-delivery-carrier-label-postlogistics
Version: 12.0.1.0.8
Summary: Print postlogistics shipping labels
Home-page: https://github.com/OCA/delivery-carrier
Author: Camptocamp,Odoo Community Association (OCA)
Author-email: support@odoo-community.org
License: AGPL-3
Platform: UNKNOWN
Classifier: Programming Language :: Python
Classifier: Framework :: Odoo
Classifier: License :: OSI Approved :: GNU Affero General Public License v3
Requires-Python: >=3.5
Requires-Dist: odoo12-addon-base-delivery-carrier-label
Requires-Dist: odoo12-addon-configuration-helper
Requires-Dist: odoo (<12.1dev,>=12.0a)
Requires-Dist: unidecode
